CIUimage/CIUimage.py
CIUimage/__init__.py
py_ciu_image-0.1.1.dist-info/LICENSE
py_ciu_image-0.1.1.dist-info/METADATA
py_ciu_image-0.1.1.dist-info/WHEEL
py_ciu_image-0.1.1.dist-info/top_level.txt
py_ciu_image-0.1.1.dist-info/RECORD
